pymodaq_femto/VERSION
pymodaq_femto/__init__.py
pymodaq_femto/converter.py
pymodaq_femto/graphics.py
pymodaq_femto/materials.py
pymodaq_femto/pnps.py
pymodaq_femto/retriever.py
pymodaq_femto/simulator.py
pymodaq_femto/viewers.py
pymodaq_femto/resources/load_settings.png
pymodaq_femto/resources/save_settings.png
pymodaq_femto/utils/example_conversion.py
pymodaq_femto/utils/example_fundamental_numpy.npz
pymodaq_femto/utils/example_trace_numpy.npz
pymodaq_femto/utils/raw_scans/example_measured_dscan_to_convert.h5
pymodaq_femto-5.1.0.dist-info/licenses/LICENSE
pymodaq_femto-5.1.0.dist-info/METADATA
pymodaq_femto-5.1.0.dist-info/WHEEL
pymodaq_femto-5.1.0.dist-info/entry_points.txt
pymodaq_femto-5.1.0.dist-info/top_level.txt
pymodaq_femto-5.1.0.dist-info/RECORD
