Metadata-Version: 2.4
Name: pymodaq_femto
Version: 5.1.0
Summary: PyMoDAQ extension for femtosecond laser pulse characterization
Home-page: http://pymodaq.cnrs.fr
Author: Sébastien Weber
Author-email: sebastien.weber@cemes.fr
License: CeCILL-B
Classifier: Programming Language :: Python :: 3
Classifier: Development Status :: 5 - Production/Stable
Classifier: Environment :: Other Environment
Classifier: Intended Audience :: Science/Research
Classifier: Topic :: Scientific/Engineering :: Human Machine Interfaces
Classifier: Topic :: Scientific/Engineering :: Visualization
Classifier: License :: OSI Approved :: MIT License
Classifier: Operating System :: OS Independent
Classifier: Topic :: Software Development :: Libraries :: Python Modules
Classifier: Topic :: Software Development :: User Interfaces
Requires-Python: >=3.6
License-File: LICENSE
Requires-Dist: pymodaq>=5.1.0
Requires-Dist: matplotlib
Requires-Dist: pypret_pymodaq
Requires-Dist: pyqt5
Dynamic: license-file
